jmeslog/__init__.py
jmeslog/__main__.py
jmeslog/cli.py
jmeslog/constants.py
jmeslog/core.py
jmeslog/errors.py
jmeslog/model.py
jmeslog-0.2.0.dist-info/LICENSE
jmeslog-0.2.0.dist-info/METADATA
jmeslog-0.2.0.dist-info/NOTICE
jmeslog-0.2.0.dist-info/WHEEL
jmeslog-0.2.0.dist-info/entry_points.txt
jmeslog-0.2.0.dist-info/RECORD
