Metadata-Version: 2.1
Name: jmeslog
Version: 0.2.0
Summary: Tool for managing changelogs
Home-page: https://jamesls.github.io/jmeslog
License: Apache-2.0
Author: James Saryerwinnie
Author-email: js@jamesls.com
Requires-Python: >=3.9.0,<4.0
Classifier: Development Status :: 3 - Alpha
Classifier: Intended Audience :: Developers
Classifier: License :: OSI Approved :: Apache Software License
Classifier: Operating System :: OS Independent
Classifier: Programming Language :: Python
Classifier: Programming Language :: Python :: 3
Classifier: Programming Language :: Python :: 3.9
Classifier: Programming Language :: Python :: 3.10
Classifier: Programming Language :: Python :: 3.11
Classifier: Programming Language :: Python :: 3.12
Classifier: Topic :: Software Development :: Libraries :: Python Modules
Classifier: Typing :: Typed
Requires-Dist: Jinja2 (>=3.1.4,<4.0.0)
Requires-Dist: packaging (>=24.0,<25.0)
Project-URL: Documentation, https://jamesls.github.io/jmeslog
Project-URL: Repository, https://github.com/jamesls/jmeslog
